{"nodes": [{"id": "tag_schema_htr_error_tags", "label": "HTR Error Tag Schema (S1/S2/S3 Classification)", "file_type": "code", "source_file": "pipeline/htr_descriptive_analysis/pre/schemas_and_manifests/tag_schema.json", "source_location": "line 1", "source_url": null, "captured_at": null, "author": null, "contributor": null}, {"id": "tag_schema_s1_whitespace_tags", "label": "Tag Group S1: Whitespace and Punctuation Errors", "file_type": "concept", "source_file": "pipeline/htr_descriptive_analysis/pre/schemas_and_manifests/tag_schema.json", "source_location": "line 2", "source_url": null, "captured_at": null, "author": null, "contributor": null}, {"id": "tag_schema_s2_character_error_tags", "label": "Tag Group S2: Character-Level HTR Errors (XID)", "file_type": "concept", "source_file": "pipeline/htr_descriptive_analysis/pre/schemas_and_manifests/tag_schema.json", "source_location": "line 13", "source_url": null, "captured_at": null, "author": null, "contributor": null}, {"id": "tag_schema_s3_orthographic_tags", "label": "Tag Group S3: Historical Orthographic Patterns", "file_type": "concept", "source_file": "pipeline/htr_descriptive_analysis/pre/schemas_and_manifests/tag_schema.json", "source_location": "line 19", "source_url": null, "captured_at": null, "author": null, "contributor": null}], "edges": [{"source": "tag_schema_htr_error_tags", "target": "tag_schema_s1_whitespace_tags", "relation": "implements", "confidence": "EXTRACTED", "confidence_score": 1.0, "source_file": "pipeline/htr_descriptive_analysis/pre/schemas_and_manifests/tag_schema.json", "source_location": "line 2", "weight": 1.0}, {"source": "tag_schema_htr_error_tags", "target": "tag_schema_s2_character_error_tags", "relation": "implements", "confidence": "EXTRACTED", "confidence_score": 1.0, "source_file": "pipeline/htr_descriptive_analysis/pre/schemas_and_manifests/tag_schema.json", "source_location": "line 13", "weight": 1.0}, {"source": "tag_schema_htr_error_tags", "target": "tag_schema_s3_orthographic_tags", "relation": "implements", "confidence": "EXTRACTED", "confidence_score": 1.0, "source_file": "pipeline/htr_descriptive_analysis/pre/schemas_and_manifests/tag_schema.json", "source_location": "line 19", "weight": 1.0}, {"source": "tag_schema_s2_character_error_tags", "target": "schema_sql_public_descriptive_analysis", "relation": "shares_data_with", "confidence": "INFERRED", "confidence_score": 0.85, "source_file": "pipeline/htr_descriptive_analysis/pre/schemas_and_manifests/tag_schema.json", "source_location": "line 13", "weight": 1.0}, {"source": "tag_schema_s3_orthographic_tags", "target": "htr_nlp_histclean_spa", "relation": "semantically_similar_to", "confidence": "INFERRED", "confidence_score": 0.75, "source_file": "pipeline/htr_descriptive_analysis/pre/schemas_and_manifests/tag_schema.json", "source_location": "line 19", "weight": 1.0}], "hyperedges": []}